docs/conf.py
pycs3/__init__.py
pycs3/gen/__init__.py
pycs3/gen/datapoints.py
pycs3/gen/lc.py
pycs3/gen/lc_func.py
pycs3/gen/mrg.py
pycs3/gen/polyml.py
pycs3/gen/sea.py
pycs3/gen/spl.py
pycs3/gen/spl_func.py
pycs3/gen/splml.py
pycs3/gen/stat.py
pycs3/gen/util.py
pycs3/pipe/__init__.py
pycs3/pipe/optimiser.py
pycs3/pipe/pipe_utils.py
pycs3/regdiff/__init__.py
pycs3/regdiff/multiopt.py
pycs3/regdiff/rslc.py
pycs3/regdiff/scikitgp.py
pycs3/sim/__init__.py
pycs3/sim/draw.py
pycs3/sim/plot.py
pycs3/sim/power_spec.py
pycs3/sim/run.py
pycs3/sim/src.py
pycs3/sim/twk.py
pycs3/spl/__init__.py
pycs3/spl/multiopt.py
pycs3/spl/topopt.py
pycs3/tdcomb/__init__.py
pycs3/tdcomb/comb.py
pycs3/tdcomb/plot.py
pycs3-3.0.4.dist-info/licenses/AUTHORS.rdb
pycs3-3.0.4.dist-info/licenses/LICENSE
scripts/1_create_dataset.py
scripts/1_create_dataset_padma.py
scripts/2_fit_spline.py
scripts/3_all.py
scripts/3a_generate_tweakml.py
scripts/3b_draw_copy_mocks.py
scripts/3c_optimise_copy_mocks.py
scripts/3d_check_statistics.py
scripts/3e_launch_opt_regdiff_para.py
scripts/4a_plot_results.py
scripts/4b_marginalise_spline.py
scripts/4c_marginalise_regdiff.py
scripts/4d_marginalise_all.py
scripts/5_combine_dataset.py
scripts/config_combination_default.py
scripts/config_default_double.py
scripts/config_default_quads.py
scripts/config_default_triple.py
scripts/exec_regdiff.py
scripts/test.py
scripts/Combination/HE0047/config_combination_HE0047.py
scripts/Combination/J1650/config_combination_J1650.py
scripts/Combination/J1721/config_combination_J1721.py
scripts/config/config_2M1134_WFI.py
scripts/config/config_DESJ0029_WFI2.py
scripts/config/config_DESJ0029_WFI4.py
scripts/config/config_HE0047_WFI.py
scripts/config/config_HE0435_ALL.py
scripts/config/config_J1433_Maidanak2025+WendelsteinG.py
scripts/config/config_J1433_Maidanak2025.py
scripts/config/config_J1433_WendelsteinG.py
scripts/config/config_J1650_Maidanak+Mercator+USNO.py
scripts/config/config_J1650_Maidanak+Mercator+USNOlight.py
scripts/config/config_J1650_Maidanak+Mercator.py
scripts/config/config_J1650_Maidanak+USNO.py
pycs3-3.0.4.dist-info/METADATA
pycs3-3.0.4.dist-info/WHEEL
pycs3-3.0.4.dist-info/top_level.txt
pycs3-3.0.4.dist-info/RECORD
