Metadata-Version: 2.4
Name: PyCS3
Version: 3.0.4
Summary: PyCS3: A Python toolbox for time-delay measurements in lensed quasars
Home-page: https://gitlab.com/cosmograil/PyCS3
Author: Malte Tewes, Vivien Bonvin
Author-email: Martin Millon <martin.millon@hotmail.fr>
License-Expression: GPL-3.0-or-later
Project-URL: Homepage, https://gitlab.com/cosmograil/PyCS3
Project-URL: Repository, https://gitlab.com/cosmograil/PyCS3
Keywords: time-delay measurements,astronomy,light curves
Classifier: Intended Audience :: Science/Research
Classifier: Programming Language :: Python :: 3
Classifier: Programming Language :: Python :: 3.11
Classifier: Topic :: Scientific/Engineering :: Astronomy
Requires-Python: >=3.11
License-File: LICENSE
License-File: AUTHORS.rdb
Requires-Dist: matplotlib>=3.4.2
Requires-Dist: numpy>=2.3
Requires-Dist: scipy>=1.7
Requires-Dist: multiprocess>=0.70.16
Requires-Dist: scikit-learn>=1.7.2
Provides-Extra: test
Requires-Dist: pytest; extra == "test"
Requires-Dist: pytest-cov; extra == "test"
Dynamic: license-file
